chat_ai/__init__.py
chat_ai/_version.py
chat_ai/client.py
chat_ai/utils.py
chat_ai_joseph123-0.1.1.dist-info/licenses/LICENSE
chat_ai_joseph123-0.1.1.dist-info/METADATA
chat_ai_joseph123-0.1.1.dist-info/WHEEL
chat_ai_joseph123-0.1.1.dist-info/top_level.txt
chat_ai_joseph123-0.1.1.dist-info/RECORD
