Metadata-Version: 2.4
Name: chat-ai-joseph123
Version: 0.1.1
Summary: AI helper utilities for text generation
Author: Joseph Paul
Requires-Python: >=3.8
License-File: LICENSE
Requires-Dist: requests
Requires-Dist: python-dotenv
Dynamic: license-file
